PyCXpress/__init__.py
PyCXpress/__main__.py
PyCXpress/core.py
PyCXpress/debugger.py
PyCXpress/example/Makefile
PyCXpress/example/main.cpp
PyCXpress/example/model.py
PyCXpress/include/PyCXpress/core.hpp
PyCXpress/include/PyCXpress/utils.hpp
PyCXpress/interface.py
PyCXpress/utils.py
pycxpress-0.0.8.dist-info/LICENSE
pycxpress-0.0.8.dist-info/METADATA
pycxpress-0.0.8.dist-info/WHEEL
pycxpress-0.0.8.dist-info/entry_points.txt
pycxpress-0.0.8.dist-info/RECORD
