Metadata-Version: 2.1
Name: PyCXpress
Version: 0.0.8
Summary: PyCXpress is a high-performance hybrid framework that seamlessly integrates Python and C++ to harness the flexibility of Python and the speed of C++ for efficient and expressive computation, particularly in the realm of deep learning and numerical computing.
Home-page: https://github.com/chaoqing/PyCXpress
License: MIT
Keywords: CPP,Embdedding
Author: chaoqing
Author-email: chaoqingwang.nick@gmail.com
Requires-Python: >=3.8,<4.0
Classifier: Development Status :: 3 - Alpha
Classifier: Intended Audience :: Developers
Classifier: License :: OSI Approved :: MIT License
Classifier: Operating System :: OS Independent
Classifier: Programming Language :: Python :: 3
Classifier: Programming Language :: Python :: 3.8
Classifier: Programming Language :: Python :: 3.9
Classifier: Programming Language :: Python :: 3.10
Classifier: Programming Language :: Python :: 3.11
Classifier: Programming Language :: Python :: 3.12
Classifier: Topic :: Software Development :: Libraries :: Python Modules
Requires-Dist: numpy (<1.22) ; python_version >= "3.8" and python_version < "3.9"
Requires-Dist: numpy (>=1.22,<2.0) ; python_version >= "3.9"
Requires-Dist: pybind11 (>=2.12.0,<3.0.0)
Project-URL: Repository, https://github.com/chaoqing/PyCXpress
